setup.py
toripy/__init__.py
toripy.egg-info/PKG-INFO
toripy.egg-info/SOURCES.txt
toripy.egg-info/dependency_links.txt
toripy.egg-info/not-zip-safe
toripy.egg-info/requires.txt
toripy.egg-info/top_level.txt