Metadata-Version: 1.0
Name: toripy
Version: 0.1.1
Summary: Lightweight python interface to easily make HTTP(s) requests over the Tor network.
Home-page: http://github.com/nikoferro/toripy
Author: Nicolas Ferro
Author-email: nicolaspatricioferro@gmail.com
License: MIT
Platform: UNKNOWN
